flask_restly/__init__.py
flask_restly/_rate.py
flask_restly/_storage.py
flask_restly/_url_rule.py
flask_restly/_view.py
flask_restly/decorator/__init__.py
flask_restly/decorator/auth.py
flask_restly/decorator/body.py
flask_restly/decorator/delete.py
flask_restly/decorator/get.py
flask_restly/decorator/identity.py
flask_restly/decorator/patch.py
flask_restly/decorator/post.py
flask_restly/decorator/put.py
flask_restly/decorator/queued.py
flask_restly/decorator/rate.py
flask_restly/decorator/resource.py
flask_restly/exception/__init__.py
flask_restly/exception/bad_request.py
flask_restly/exception/conflict.py
flask_restly/exception/forbidden.py
flask_restly/exception/internal_server_error.py
flask_restly/exception/not_acceptable.py
flask_restly/exception/not_found.py
flask_restly/exception/not_implemented.py
flask_restly/exception/too_many_requests.py
flask_restly/exception/unauthorized.py
flask_restly/exception/unprocessable_entity.py
flask_restly/serializer/__init__.py
flask_restly-1.1.0.dist-info/LICENSE
flask_restly-1.1.0.dist-info/METADATA
flask_restly-1.1.0.dist-info/WHEEL
flask_restly-1.1.0.dist-info/top_level.txt
flask_restly-1.1.0.dist-info/RECORD
