Metadata-Version: 2.1
Name: flask-restly
Version: 1.1.0
Summary: Build a REST API with Flask
Home-page: https://github.com/gorzechowski/flask-restly
Author: Gracjan Orzechowski
Author-email: orzechowski.gracjan@gmail.com
License: MIT
Keywords: flask api rest
Platform: UNKNOWN
Classifier: Development Status :: 5 - Production/Stable
Classifier: Environment :: Web Environment
Classifier: Framework :: Flask
Classifier: Intended Audience :: Developers
Classifier: License :: OSI Approved :: MIT License
Classifier: Operating System :: OS Independent
Classifier: Programming Language :: Python :: 3
Classifier: Programming Language :: Python :: 3.4
Classifier: Programming Language :: Python :: 3.5
Classifier: Programming Language :: Python :: 3.6
Classifier: Programming Language :: Python :: 3.7
Classifier: Topic :: Internet :: WWW/HTTP
Classifier: Topic :: Software Development :: Libraries
Classifier: Topic :: Software Development :: Libraries :: Application Frameworks
Requires-Dist: flask (>=1.0)
Requires-Dist: wrapt (>=1.0)
